pivuq/__about__.py
pivuq/__init__.py
pivuq/disparity.py
pivuq/lib.py
pivuq/warping.py
pivuq-0.4.1.dist-info/LICENSE
pivuq-0.4.1.dist-info/WHEEL
pivuq-0.4.1.dist-info/METADATA
pivuq-0.4.1.dist-info/RECORD
