Metadata-Version: 2.1
Name: pivuq
Version: 0.4.1
Summary: A library for PIV Uncertainty Quantification
Home-page: https://github.com/lento234/pivuq
License: MIT
Keywords: PIV,UQ
Author: MrLento234
Author-email: lento.manickathan@gmail.com
Requires-Python: >=3.10,<4.0
Classifier: Intended Audience :: Science/Research
Classifier: License :: OSI Approved :: MIT License
Classifier: Operating System :: POSIX :: Linux
Classifier: Programming Language :: Python :: 3
Classifier: Programming Language :: Python :: 3.10
Classifier: Programming Language :: Python :: 3.11
Classifier: Programming Language :: Python :: 3.10
Classifier: Programming Language :: Python :: 3.8
Classifier: Programming Language :: Python :: 3.9
Classifier: Topic :: Scientific/Engineering :: Image Processing
Classifier: Topic :: Scientific/Engineering :: Physics
Requires-Dist: numba (>=0.56.3,<0.57.0)
Requires-Dist: numpy (>=1.23.4,<2.0.0)
Requires-Dist: scikit-image (>=0.19.3,<0.20.0)
Requires-Dist: scipy (>=1.9.3,<2.0.0)
Project-URL: Documentation, https://pivuq.readthedocs.io
